quli_quiz/__init__.py
quli_quiz/cli.py
quli_quiz/config.py
quli_quiz/engine.py
quli_quiz/generator.py
quli_quiz/models.py
quli_quiz/streamlit_app.py
quli_quiz/modes/__init__.py
quli_quiz/modes/batch.py
quli_quiz/modes/interactive.py
quli_quiz/ui/__init__.py
quli_quiz/ui/display.py
quli_quiz/ui/input.py
quli_quiz/ui/styles.py
quli_quiz/ui/streamlit/__init__.py
quli_quiz/ui/streamlit/config.py
quli_quiz/ui/streamlit/question.py
quli_quiz/ui/streamlit/results.py
quli_quiz/ui/streamlit/utils.py
quli_quiz/utils/__init__.py
quli_quiz/utils/selection.py
quli_quiz-2.1.0.dist-info/METADATA
quli_quiz-2.1.0.dist-info/WHEEL
quli_quiz-2.1.0.dist-info/entry_points.txt
quli_quiz-2.1.0.dist-info/licenses/LICENSE
quli_quiz-2.1.0.dist-info/RECORD
