Metadata-Version: 2.4
Name: quli-quiz
Version: 2.1.0
Summary: CLI quiz app powered by Gemini Flash 2.5
Author-email: Jakeer C <jakeer.builds@gmail.com>
License: MIT
License-File: LICENSE
Keywords: cli,education,gemini,quiz
Classifier: Development Status :: 4 - Beta
Classifier: Intended Audience :: Education
Classifier: License :: OSI Approved :: MIT License
Classifier: Programming Language :: Python :: 3
Classifier: Programming Language :: Python :: 3.10
Classifier: Programming Language :: Python :: 3.11
Classifier: Programming Language :: Python :: 3.12
Requires-Python: >=3.10
Requires-Dist: click>=8.0.0
Requires-Dist: google-genai==1.49.0
Requires-Dist: plotly>=5.0.0
Requires-Dist: prompt-toolkit>=3.0.0
Requires-Dist: pydantic>=2.0.0
Requires-Dist: python-dotenv>=1.0.0
Requires-Dist: rich>=13.0.0
Requires-Dist: streamlit>=1.28.0
Provides-Extra: dev
Requires-Dist: pytest>=7.0.0; extra == 'dev'
